{
  "opening": "Caro-Kann Defense",
  "key_mistakes": [
    {
      "move": "c6",
      "reason": "Black aims for the Caro-Kann but plays passively, allowing White to gain central control.",
      "better_move": "e5",
      "type": "strategic"
    },
    {
      "move": "exd5",
      "reason": "Capturing prematurely instead of maintaining central tension.",
      "better_move": "e5",
      "type": "strategic"
    },
    {
      "move": "Nc6",
      "reason": "Develops the knight to c6 where it can be pinned by Bb5.",
      "better_move": "Nf6",
      "type": "strategic"
    },
    {
      "move": "O-O",
      "reason": "Castling into an already developed position, missing a more aggressive continuation.",
      "better_move": "h4",
      "type": "strategic"
    },
    {
      "move": "Rc8",
      "reason": "Loses tempo with an unnecessary rook move, missing more active queen placement.",
      "better_move": "Qc7",
      "type": "strategic"
    },
    {
      "move": "Bh6",
      "reason": "Misplaces the bishop without a clear plan.",
      "better_move": "Nf3",
      "type": "strategic"
    },
    {
      "move": "Qf4",
      "reason": "Blunders material by allowing a knight to capture the queen.",
      "better_move": "Qh3",
      "type": "tactical"
    },
    {
      "move": "Nxd4",
      "reason": "Trades a knight for a pawn, missing a more effective attack on the bishop.",
      "better_move": "Bg5",
      "type": "tactical"
    },
    {
      "move": "Nc6",
      "reason": "Returns the knight to an ineffective square, missing a tactical opportunity.",
      "better_move": "Bg5",
      "type": "tactical"
    },
    {
      "move": "Nf3",
      "reason": "Misses the opportunity to improve the position of the rooks.",
      "better_move": "Rfd1",
      "type": "strategic"
    },
    {
      "move": "Qh3",
      "reason": "Relocates the queen to a passive position.",
      "better_move": "Qd2",
      "type": "strategic"
    },
    {
      "move": "Nd4",
      "reason": "Blunders a knight, allowing opponent's knight to capture it.",
      "better_move": "Nd2",
      "type": "tactical"
    }
  ],
  "themes": [
    "central control",
    "piece activity",
    "development",
    "pawn structure"
  ],
  "recommendations": [
    "Focus on controlling the center with pawn moves like e4 and d4.",
    "Develop pieces actively to squares where they can exert maximum influence.",
    "Avoid unnecessary pawn captures that release central tension prematurely.",
    "Be aware of tactical opportunities and threats, especially involving unprotected pieces."
  ]
}